newton_sos-0.2.2.dist-info/METADATA
newton_sos-0.2.2.dist-info/WHEEL
newton_sos-0.2.2.dist-info/licenses/LICENSE
newton_sos/__init__.py
newton_sos/newton_sos.cpython-313-darwin.so
newton_sos/tests.py
newton_sos-0.2.2.dist-info/RECORD
