Metadata-Version: 2.4
Name: newton_sos
Version: 0.2.2
Classifier: Programming Language :: Rust
Classifier: Programming Language :: Python :: Implementation :: CPython
Classifier: Programming Language :: Python :: Implementation :: PyPy
License-File: LICENSE
Summary: Damped Newton method to solve low-rank problems arising from KernelSOS and Sum-of-Squares relaxations
Home-Page: https://github.com/agroudiev/newton-sos
Author-email: Antoine Groudiev <antoine.groudiev@ens.psl.eu>
Requires-Python: >=3.8
